{
    "interactionModel": {
        "languageModel": {
            "invocationName": "color",
            "intents": [
                {
                    "name": "MyColorIsIntent",
                    "slots": [
                        {
                            "name": "Color",
                            "type": "LIST_OF_COLORS"
                        }
                    ],
                    "samples": [
                        "my favorite color is {Color}"
                    ]
                },
                {
                    "name": "WhatsMyColorIntent",
                    "slots": [],
                    "samples": [
                        "my color",
                        "what is my favorite color",
                        "what's my favorite color"
                    ]
                },
                {
                    "name": "AMAZON.FallbackIntent",
                    "samples": []
                },
                {
                    "name": "AMAZON.CancelIntent",
                    "samples": []
                },
                {
                    "name": "AMAZON.HelpIntent",
                    "samples": []
                },
                {
                    "name": "AMAZON.StopIntent",
                    "samples": []
                },
                {
                    "name": "AMAZON.NavigateHomeIntent",
                    "samples": []
                }
            ],
            "types": [
                {
                    "name": "LIST_OF_COLORS",
                    "values": [
                        {
                            "name": {
                                "value": "silver"
                            }
                        },
                        {
                            "name": {
                                "value": "orange"
                            }
                        },
                        {
                            "name": {
                                "value": "black"
                            }
                        },
                        {
                            "name": {
                                "value": "white"
                            }
                        },
                        {
                            "name": {
                                "value": "yellow"
                            }
                        },
                        {
                            "name": {
                                "value": "blue"
                            }
                        },
                        {
                            "name": {
                                "value": "red"
                            }
                        },
                        {
                            "name": {
                                "value": "green"
                            }
                        }
                    ]
                }
            ]
        }
    }
}
